merge_config/__init__.py
merge_config/base_plugin.py
merge_config/load_config.py
merge_config/plugins/__init__.py
merge_config/plugins/aws.py
merge_config/plugins/env.py
merge_config/plugins/file.py
merge_config-0.3.0.dist-info/WHEEL
merge_config-0.3.0.dist-info/METADATA
merge_config-0.3.0.dist-info/RECORD
