Metadata-Version: 2.1
Name: merge-config
Version: 0.3.0
Summary: 
Author: Barath Kumar
Author-email: barath@mergedup.com
Requires-Python: >=3.9,<4.0
Classifier: Programming Language :: Python :: 3
Classifier: Programming Language :: Python :: 3.9
Classifier: Programming Language :: Python :: 3.10
Requires-Dist: PyYAML (>=6.0,<7.0)
Requires-Dist: deepmerge (>=1.0.1,<2.0.0)
Requires-Dist: flatten-dict (>=0.4.2,<0.5.0)
Requires-Dist: pydantic (>=1.10.2,<2.0.0)
Requires-Dist: python-dotenv (>=0.21.0,<0.22.0)
